setup.py
onewire/__init__.py
onewire/_ow.c
onewire.egg-info/PKG-INFO
onewire.egg-info/SOURCES.txt
onewire.egg-info/dependency_links.txt
onewire.egg-info/top_level.txt