Metadata-Version: 1.0
Name: onewire
Version: 0.2
Summary: A wrapper for OWFS C-API, compatible with both Python 2.7 and Python 3.x.
Home-page: https://github.com/kipe/python-onewire
Author: Kimmo Huoman
Author-email: kipenroskaposti@gmail.com
License: UNKNOWN
Platform: UNKNOWN
